Metadata-Version: 2.1
Name: glustercli2
Version: 0.3.0
Summary: Python bindings for GlusterFS CLI
Home-page: https://github.com/aravindavk/glustercli2-python
Author: Aravinda Vishwanathapura
Author-email: mail@aravindavk.in
License: Apache-2.0
Platform: UNKNOWN
Classifier: Development Status :: 5 - Production/Stable
Classifier: Intended Audience :: Developers
Classifier: License :: OSI Approved :: Apache Software License
Classifier: Operating System :: POSIX :: Linux
Classifier: Programming Language :: Python
Classifier: Programming Language :: Python :: 3
Classifier: Topic :: System :: Filesystems
